pymilo/__init__.py
pymilo/__main__.py
pymilo/pymilo_func.py
pymilo/pymilo_obj.py
pymilo/pymilo_param.py
pymilo/chains/__init__.py
pymilo/chains/chain.py
pymilo/chains/clustering_chain.py
pymilo/chains/compose_chain.py
pymilo/chains/cross_decomposition_chain.py
pymilo/chains/decision_tree_chain.py
pymilo/chains/ensemble_chain.py
pymilo/chains/linear_model_chain.py
pymilo/chains/naive_bayes_chain.py
pymilo/chains/neighbours_chain.py
pymilo/chains/neural_network_chain.py
pymilo/chains/svm_chain.py
pymilo/chains/util.py
pymilo/exceptions/__init__.py
pymilo/exceptions/deserialize_exception.py
pymilo/exceptions/pymilo_exception.py
pymilo/exceptions/serialize_exception.py
pymilo/streaming/__init__.py
pymilo/streaming/communicator.py
pymilo/streaming/compressor.py
pymilo/streaming/encryptor.py
pymilo/streaming/interfaces.py
pymilo/streaming/param.py
pymilo/streaming/pymilo_client.py
pymilo/streaming/pymilo_server.py
pymilo/streaming/util.py
pymilo/transporters/__init__.py
pymilo/transporters/adamoptimizer_transporter.py
pymilo/transporters/baseloss_transporter.py
pymilo/transporters/binmapper_transporter.py
pymilo/transporters/bisecting_tree_transporter.py
pymilo/transporters/bunch_transporter.py
pymilo/transporters/cfnode_transporter.py
pymilo/transporters/compose_transporter.py
pymilo/transporters/feature_extraction_transporter.py
pymilo/transporters/function_transporter.py
pymilo/transporters/general_data_structure_transporter.py
pymilo/transporters/generator_transporter.py
pymilo/transporters/lossfunction_transporter.py
pymilo/transporters/neighbors_tree_transporter.py
pymilo/transporters/preprocessing_transporter.py
pymilo/transporters/randomstate_transporter.py
pymilo/transporters/sgdoptimizer_transporter.py
pymilo/transporters/transporter.py
pymilo/transporters/tree_transporter.py
pymilo/transporters/treepredictor_transporter.py
pymilo/utils/__init__.py
pymilo/utils/data_exporter.py
pymilo/utils/test_pymilo.py
pymilo/utils/util.py
pymilo-1.5.dist-info/licenses/AUTHORS.md
pymilo-1.5.dist-info/licenses/LICENSE
pymilo-1.5.dist-info/METADATA
pymilo-1.5.dist-info/WHEEL
pymilo-1.5.dist-info/entry_points.txt
pymilo-1.5.dist-info/top_level.txt
pymilo-1.5.dist-info/RECORD
