Metadata-Version: 2.4
Name: pymilo
Version: 1.5
Summary: PyMilo: Python for ML I/O
Home-page: https://github.com/openscilab/pymilo
Download-URL: https://github.com/openscilab/pymilo/tarball/v1.5
Author: PyMilo Development Team
Author-email: pymilo@openscilab.com
License: MIT
Project-URL: Source, https://github.com/openscilab/pymilo
Keywords: machine_learning ml ai mlops model export import
Classifier: Development Status :: 3 - Alpha
Classifier: Natural Language :: English
Classifier: License :: OSI Approved :: MIT License
Classifier: Operating System :: OS Independent
Classifier: Programming Language :: Python :: 3.7
Classifier: Programming Language :: Python :: 3.8
Classifier: Programming Language :: Python :: 3.9
Classifier: Programming Language :: Python :: 3.10
Classifier: Programming Language :: Python :: 3.11
Classifier: Programming Language :: Python :: 3.12
Classifier: Programming Language :: Python :: 3.13
Classifier: Programming Language :: Python :: 3.14
Classifier: Intended Audience :: Developers
Classifier: Intended Audience :: Education
Classifier: Intended Audience :: End Users/Desktop
Classifier: Intended Audience :: Manufacturing
Classifier: Intended Audience :: Science/Research
Classifier: Topic :: Scientific/Engineering :: Information Analysis
Classifier: Topic :: Education
Classifier: Topic :: Scientific/Engineering
Classifier: Topic :: Scientific/Engineering :: Artificial Intelligence
Classifier: Topic :: Scientific/Engineering :: Human Machine Interfaces
Classifier: Topic :: Scientific/Engineering :: Mathematics
Classifier: Topic :: Scientific/Engineering :: Physics
Requires-Python: >=3.7
License-File: LICENSE
License-File: AUTHORS.md
Requires-Dist: art>=1.8
Requires-Dist: numpy>=1.9.0
Requires-Dist: requests>=2.0.0
Requires-Dist: scikit-learn>=0.22.2
Requires-Dist: scipy>=0.19.1
Provides-Extra: streaming
Requires-Dist: uvicorn>=0.14.0; extra == "streaming"
Requires-Dist: fastapi>=0.68.0; extra == "streaming"
Requires-Dist: pydantic>=1.5.0; extra == "streaming"
Requires-Dist: websockets>=9.0; extra == "streaming"
Dynamic: author
Dynamic: author-email
Dynamic: classifier
Dynamic: description
Dynamic: description-content-type
Dynamic: download-url
Dynamic: home-page
Dynamic: keywords
Dynamic: license
Dynamic: license-file
Dynamic: project-url
Dynamic: provides-extra
Dynamic: requires-dist
Dynamic: requires-python
Dynamic: summary
